intonation/__init__.py
intonation/pitch.py
intonation/recording.py
intonation/utils.py
intonation/examples/88d8196a-123a-4306-9856-4ce3faca14fc.txt
intonation/examples/howto.ipynb
intonation/examples/howto.py
intonation/examples/howto.rst
intonation/examples/.ipynb_checkpoints/howto-checkpoint.ipynb
intonation/examples/howto_files/howto_11_0.png
intonation/examples/howto_files/howto_11_0.text
intonation/examples/howto_files/howto_11_1.text
intonation/examples/howto_files/howto_1_0.text
intonation/examples/howto_files/howto_5_0.text
intonation/examples/howto_files/howto_5_1.png
intonation/examples/howto_files/howto_5_1.text
intonation/examples/howto_files/howto_7_0.text
intonation/examples/howto_files/howto_9_0.text
intonation-2024.9.8.dist-info/LICENSE
intonation-2024.9.8.dist-info/METADATA
intonation-2024.9.8.dist-info/WHEEL
intonation-2024.9.8.dist-info/top_level.txt
intonation-2024.9.8.dist-info/RECORD
