Metadata-Version: 2.1
Name: intonation
Version: 2024.9.8
Summary: Python module to analyze, study and research the intonation of musical intervals in music recordings.
Author-email: Gopala Krishna Koduri <gopala.koduri@gmail.com>
License: GNU Affero GPL v3
Project-URL: Homepage, https://github.com/gopalkoduri/intonation
Keywords: python,intonation,research,music,intervals,tuning
Classifier: Development Status :: 4 - Beta
Classifier: License :: OSI Approved :: GNU Affero General Public License v3
Classifier: Programming Language :: Python :: 3.8
Classifier: Programming Language :: Python :: 3.9
Classifier: Programming Language :: Python :: 3.10
Classifier: Programming Language :: Python :: 3.11
Classifier: Topic :: Scientific/Engineering :: Information Analysis
Classifier: Topic :: Software Development :: Libraries :: Python Modules
License-File: LICENSE
Requires-Dist: numpy
Requires-Dist: matplotlib
Requires-Dist: pypeaks
Requires-Dist: scipy
